eulerpi/__init__.py
eulerpi/core/__init__.py
eulerpi/core/data_transformations/__init__.py
eulerpi/core/data_transformations/affine_transformation.py
eulerpi/core/data_transformations/data_identity.py
eulerpi/core/data_transformations/data_normalization.py
eulerpi/core/data_transformations/data_pca.py
eulerpi/core/data_transformations/data_transformation.py
eulerpi/core/dense_grid.py
eulerpi/core/dense_grid_types.py
eulerpi/core/inference.py
eulerpi/core/inference_types.py
eulerpi/core/kde.py
eulerpi/core/model_check.py
eulerpi/core/models/__init__.py
eulerpi/core/models/artificial_model_interface.py
eulerpi/core/models/base_model.py
eulerpi/core/models/jax_extension.py
eulerpi/core/models/jax_model.py
eulerpi/core/models/sbml_model.py
eulerpi/core/plotting.py
eulerpi/core/result_manager.py
eulerpi/core/sampling.py
eulerpi/core/sparsegrid.py
eulerpi/core/transformations.py
eulerpi/examples/__init__.py
eulerpi/examples/corona/CoronaData.csv
eulerpi/examples/corona/__init__.py
eulerpi/examples/corona/corona.py
eulerpi/examples/cpp/CMakeLists.txt
eulerpi/examples/cpp/__init__.py
eulerpi/examples/cpp/cpp_model.hpp
eulerpi/examples/cpp/cpp_plant.py
eulerpi/examples/cpp/python_reference_plants.py
eulerpi/examples/cpp/wrapper.cpp
eulerpi/examples/heat/__init__.py
eulerpi/examples/heat/heat.py
eulerpi/examples/sbml/Caffeine_2Wks_Exponential_decay.xml
eulerpi/examples/sbml/__init__.py
eulerpi/examples/sbml/sbml_caffeine_model.py
eulerpi/examples/sbml/sbml_menten_model.py
eulerpi/examples/sbml/sbml_menten_model.xml
eulerpi/examples/simple_models.py
eulerpi/examples/temperature/TemperatureArtificialParams.csv
eulerpi/examples/temperature/TemperatureData.csv
eulerpi/examples/temperature/__init__.py
eulerpi/examples/temperature/temperature.py
eulerpi-0.10.0.dist-info/LICENSE.md
eulerpi-0.10.0.dist-info/METADATA
eulerpi-0.10.0.dist-info/WHEEL
eulerpi-0.10.0.dist-info/RECORD
