Metadata-Version: 2.1
Name: eulerpi
Version: 0.10.0
Summary: The eulerian parameter inference (eulerpi) returns a parameter distribution, which is consistent with the observed data by solving the inverse problem directly. In the case of a one-to-one mapping, this is the true underlying distribution.
Author: Lars Kaiser
Author-email: lars.g.kaiser@gmx.de
Requires-Python: >=3.10,<4.0
Classifier: License :: OSI Approved :: MIT License
Classifier: Operating System :: OS Independent
Classifier: Programming Language :: Python :: 3
Classifier: Programming Language :: Python :: 3.10
Classifier: Programming Language :: Python :: 3.11
Classifier: Programming Language :: Python :: 3.12
Provides-Extra: sbml
Requires-Dist: amici (>=0.26.1) ; extra == "sbml"
Requires-Dist: diffrax (>=0.4.1)
Requires-Dist: emcee (>=3.1.4)
Requires-Dist: jax (>=0.4.19)
Requires-Dist: jaxlib (>=0.4.19)
Requires-Dist: matplotlib (>=3.8.0)
Requires-Dist: numpy (>=1.26.1)
Requires-Dist: scikit-learn (>=1.3.1,<2.0.0)
Requires-Dist: seedir (>=0.4.2)
Requires-Dist: tqdm (>=4.66.1)
Project-URL: Bug Tracker, https://github.com/Systems-Theory-in-Systems-Biology/EPI/issues
Project-URL: Changelog, https://Systems-Theory-in-Systems-Biology.github.io/EPI/MarkdownLinks/changelog.html
Project-URL: Documentation, https://Systems-Theory-in-Systems-Biology.github.io/EPI/
Project-URL: Homepage, https://github.com/Systems-Theory-in-Systems-Biology/EPI
